todo/__init__.py
todo/todo.py
todo/utils.py
todotje-1.1.0.dist-info/LICENSE
todotje-1.1.0.dist-info/METADATA
todotje-1.1.0.dist-info/WHEEL
todotje-1.1.0.dist-info/entry_points.txt
todotje-1.1.0.dist-info/top_level.txt
todotje-1.1.0.dist-info/RECORD
