Metadata-Version: 2.1
Name: todotje
Version: 1.1.0
Summary: A command-line todo list.
Author: Tom Edwards
Classifier: Programming Language :: Python :: 3
Classifier: License :: OSI Approved :: MIT License
Classifier: Operating System :: OS Independent
Requires-Python: >=3.7
License-File: LICENSE
